{
  "name": "ch2-4-2d",
  "nodes": [
    {
      "parameters": {},
      "type": "n8n-nodes-base.manualTrigger",
      "typeVersion": 1,
      "position": [
        0,
        0
      ],
      "id": "1d806775-5e5f-47a6-a75f-2636cf8d938d",
      "name": "When clicking ‘Test workflow’"
    },
    {
      "parameters": {
        "fieldToSplitOut": "items",
        "options": {}
      },
      "type": "n8n-nodes-base.splitOut",
      "typeVersion": 1,
      "position": [
        320,
        0
      ],
      "id": "579545ff-4280-4ed5-a193-6f15e86ea50f",
      "name": "Split Out"
    },
    {
      "parameters": {
        "assignments": {
          "assignments": [
            {
              "id": "160e2d24-e7ac-4882-98c0-c79fd75a3144",
              "name": "產品",
              "value": "={{ $json.product }}",
              "type": "string"
            },
            {
              "id": "4ab08a34-78f7-4649-96e3-5b6036b7fc05",
              "name": "定價",
              "value": "={{ $json.price }}",
              "type": "string"
            }
          ]
        },
        "options": {}
      },
      "type": "n8n-nodes-base.set",
      "typeVersion": 3.4,
      "position": [
        480,
        0
      ],
      "id": "e216ecbb-dad1-4132-a06e-de507ed28d1c",
      "name": "Edit Fields"
    },
    {
      "parameters": {
        "operation": "xlsx",
        "options": {}
      },
      "type": "n8n-nodes-base.convertToFile",
      "typeVersion": 1.1,
      "position": [
        640,
        0
      ],
      "id": "71330bc0-eedd-44ab-94fc-8f8e76b4d265",
      "name": "Convert to File"
    },
    {
      "parameters": {
        "operation": "write",
        "fileName": "C:/n8n-data/ch02/products.xlsx",
        "options": {}
      },
      "type": "n8n-nodes-base.readWriteFile",
      "typeVersion": 1,
      "position": [
        800,
        0
      ],
      "id": "9080ac80-ff7d-4d22-a1a5-d5d383a97f80",
      "name": "Read/Write Files from Disk"
    },
    {
      "parameters": {
        "jsCode": "return {\n  \"items\": [\n    {\n      \"product\": \"iPhone\",\n      \"price\": 999,\n      \"quantity\": 2\n    },\n    {\n      \"product\": \"MacBook\",\n      \"price\": 1299,\n      \"quantity\": 1\n    },\n    {\n      \"product\": \"AirPods\",\n      \"price\": 179,\n      \"quantity\": 3\n    }\n  ]\n};"
      },
      "type": "n8n-nodes-base.code",
      "typeVersion": 2,
      "position": [
        160,
        0
      ],
      "id": "7da24bfa-355c-4514-8db2-13f466ab8031",
      "name": "Code in JavaScript"
    }
  ],
  "pinData": {},
  "connections": {
    "When clicking ‘Test workflow’": {
      "main": [
        [
          {
            "node": "Code in JavaScript",
            "type": "main",
            "index": 0
          }
        ]
      ]
    },
    "Split Out": {
      "main": [
        [
          {
            "node": "Edit Fields",
            "type": "main",
            "index": 0
          }
        ]
      ]
    },
    "Edit Fields": {
      "main": [
        [
          {
            "node": "Convert to File",
            "type": "main",
            "index": 0
          }
        ]
      ]
    },
    "Convert to File": {
      "main": [
        [
          {
            "node": "Read/Write Files from Disk",
            "type": "main",
            "index": 0
          }
        ]
      ]
    },
    "Code in JavaScript": {
      "main": [
        [
          {
            "node": "Split Out",
            "type": "main",
            "index": 0
          }
        ]
      ]
    }
  },
  "active": false,
  "settings": {
    "executionOrder": "v1",
    "binaryMode": "separate",
    "availableInMCP": false
  },
  "versionId": "cb17d331-6da9-441d-b7fa-e1e7662734ba",
  "meta": {
    "instanceId": "b7e8bde9e1f3bc95e834c365dcac5221dc114e48bacba4a88ee234549244d416"
  },
  "id": "736JoFB4YNN5PoM3",
  "tags": []
}